pip_audit/__init__.py
pip_audit/__main__.py
pip_audit/_audit.py
pip_audit/_cache.py
pip_audit/_cli.py
pip_audit/_fix.py
pip_audit/_state.py
pip_audit/_subprocess.py
pip_audit/_util.py
pip_audit/_virtual_env.py
pip_audit/_dependency_source/__init__.py
pip_audit/_dependency_source/interface.py
pip_audit/_dependency_source/pip.py
pip_audit/_dependency_source/pyproject.py
pip_audit/_dependency_source/requirement.py
pip_audit/_format/__init__.py
pip_audit/_format/columns.py
pip_audit/_format/cyclonedx.py
pip_audit/_format/interface.py
pip_audit/_format/json.py
pip_audit/_format/markdown.py
pip_audit/_service/__init__.py
pip_audit/_service/interface.py
pip_audit/_service/osv.py
pip_audit/_service/pypi.py
pip_audit-2.7.2.dist-info/entry_points.txt
pip_audit-2.7.2.dist-info/LICENSE
pip_audit-2.7.2.dist-info/WHEEL
pip_audit-2.7.2.dist-info/METADATA
pip_audit-2.7.2.dist-info/RECORD
