Metadata-Version: 2.1
Name: pip_audit
Version: 2.7.2
Summary: A tool for scanning Python environments for known vulnerabilities
Author-email: Alex Cameron <alex.cameron@trailofbits.com>, Dustin Ingram <di@python.org>, William Woodruff <william@trailofbits.com>
Requires-Python: >=3.8
Classifier: Development Status :: 5 - Production/Stable
Classifier: Intended Audience :: Developers
Classifier: License :: OSI Approved :: Apache Software License
Classifier: Programming Language :: Python :: 3 :: Only
Classifier: Programming Language :: Python :: 3
Classifier: Programming Language :: Python :: 3.8
Classifier: Programming Language :: Python :: 3.9
Classifier: Programming Language :: Python :: 3.10
Classifier: Programming Language :: Python :: 3.11
Classifier: Programming Language :: Python :: 3.12
Classifier: Topic :: Security
Requires-Dist: CacheControl[filecache] >= 0.13.0
Requires-Dist: cyclonedx-python-lib >= 5,< 7
Requires-Dist: html5lib>=1.1
Requires-Dist: packaging>=23.0.0
Requires-Dist: pip-api>=0.0.28
Requires-Dist: pip-requirements-parser>=32.0.0
Requires-Dist: requests >= 2.31.0
Requires-Dist: rich>=12.4
Requires-Dist: toml>=0.10
Requires-Dist: build ; extra == "dev"
Requires-Dist: bump>=1.3.2 ; extra == "dev"
Requires-Dist: pip-audit[doc,test,lint] ; extra == "dev"
Requires-Dist: pdoc ; extra == "doc"
Requires-Dist: ruff < 0.2.3 ; extra == "lint"
Requires-Dist: interrogate ; extra == "lint"
Requires-Dist: mypy ; extra == "lint"
Requires-Dist: types-html5lib ; extra == "lint"
Requires-Dist: types-requests ; extra == "lint"
Requires-Dist: types-toml ; extra == "lint"
Requires-Dist: coverage[toml] ~= 7.0, != 7.3.3 ; extra == "test"
Requires-Dist: pretend ; extra == "test"
Requires-Dist: pytest ; extra == "test"
Requires-Dist: pytest-cov ; extra == "test"
Project-URL: Homepage, https://pypi.org/project/pip-audit/
Project-URL: Issues, https://github.com/pypa/pip-audit/issues
Project-URL: Source, https://github.com/pypa/pip-audit
Provides-Extra: dev
Provides-Extra: doc
Provides-Extra: lint
Provides-Extra: test
